[
  {
    "name": "4 DOGS FARM RESCUE",
    "ig_handle": "4dogsfarmrescue",
    "breed_specific": ""
  },
  {
    "name": "4 PAWS KIDDO RESCUE INC",
    "ig_handle": "4pawskiddorescueinc",
    "breed_specific": ""
  },
  {
    "name": "A LITTLE RESCUE",
    "ig_handle": "alittlerescue",
    "breed_specific": "Mostly Equine"
  },
  {
    "name": "A PURPOSEFUL",
    "ig_handle": "apurposefulrescue",
    "breed_specific": ""
  },
  {
    "name": "A PASSION FOR PAWS RESCUE INC",
    "ig_handle": "apassionforpaws",
    "breed_specific": "Akitas"
  },
  {
    "name": "AFGHAN HOUND RESCUE OF SO CAL",
    "ig_handle": "afghanhoundrescuesouthernca",
    "breed_specific": ""
  },
  {
    "name": "AKITA ANGELS INC",
    "ig_handle": "akitaangels",
    "breed_specific": "Akitas"
  },
  {
    "name": "ADY GIL WORLD CONSERVATION",
    "ig_handle": "agwcrockinrescue",
    "breed_specific": ""
  },
  {
    "name": "ALL JOY 4 PAWS",
    "ig_handle": "alljoy4paws",
    "breed_specific": "Huskies and Northern Breeds"
  },
  {
    "name": "ALL PAWS K9",
    "ig_handle": "all_paws_k9_rescue",
    "breed_specific": ""
  },
  {
    "name": "AMERICAN BRITTANY",
    "ig_handle": "americanbrittanyrescue",
    "breed_specific": ""
  },
  {
    "name": "AMERICAN MALTESE ASSOCIATION RESCUE",
    "ig_handle": "americanmalteseassoc.rescue",
    "breed_specific": ""
  },
  {
    "name": "AMORE FOR DOGS",
    "ig_handle": "amorefordogs",
    "breed_specific": "smaill pups"
  },
  {
    "name": "ANGELS FOR ANIMAL RESCUE INC",
    "ig_handle": "angelsforanimalsrescue",
    "breed_specific": ""
  },
  {
    "name": "ANGEL CITY PITS",
    "ig_handle": "angelcitypits",
    "breed_specific": ""
  },
  {
    "name": "ANIMALS RULE PLACEMENT",
    "ig_handle": "animalsrulerescue",
    "breed_specific": ""
  },
  {
    "name": "ANIMAL RESCUE VOLUNTEERS INC",
    "ig_handle": "arvsimi",
    "breed_specific": ""
  },
  {
    "name": "ASH TREE RANCH",
    "ig_handle": "FB https://www.facebook.com/AshTreeRanchRescue",
    "breed_specific": ""
  },
  {
    "name": "ATLAS ANIMAL RESCUE",
    "ig_handle": "atlasanimalrescue",
    "breed_specific": ""
  },
  {
    "name": "AUSSIE RESCUE SOCAL INC",
    "ig_handle": "aussierescuesocal",
    "breed_specific": ""
  },
  {
    "name": "BAILING OUT BENTLEY",
    "ig_handle": "bailingoutbentley",
    "breed_specific": ""
  },
  {
    "name": "BASSET HOUND RSCUE OF SOUTHERN CA",
    "ig_handle": "bassethoundrescueofsocal",
    "breed_specific": ""
  },
  {
    "name": "BALOOJA'S FOUNDATION",
    "ig_handle": "baloojasfoundation",
    "breed_specific": ""
  },
  {
    "name": "BARKS OF LOVE",
    "ig_handle": "barksoflove",
    "breed_specific": ""
  },
  {
    "name": "BEACHFRONT MUTTS",
    "ig_handle": "beachfrontmuttsrescue",
    "breed_specific": ""
  },
  {
    "name": "BEAGLE FREEDOM PROJECT",
    "ig_handle": "beaglefreedom",
    "breed_specific": ""
  },
  {
    "name": "BEANS BEAGLES",
    "ig_handle": "beansbeaglesdogrescue_",
    "breed_specific": ""
  },
  {
    "name": "BEEZYS RESCUE CORP",
    "ig_handle": "beezys_rescue",
    "breed_specific": ""
  },
  {
    "name": "BELLA AND SUNSHINE RESCUE INC",
    "ig_handle": "bellaandsunshinerescue",
    "breed_specific": "DOBERMAN"
  },
  {
    "name": "BEOPLES BUDDIES ANIMAL RESCUE",
    "ig_handle": "beoplesbuddies",
    "breed_specific": "SENIOR ANIMAL ADOPTION"
  },
  {
    "name": "BENNYS FRIENDS",
    "ig_handle": "bennysfriends",
    "breed_specific": ""
  },
  {
    "name": "BETTERTOGETHER FOUNDATION",
    "ig_handle": "peopleandpetsbtf",
    "breed_specific": "Seniors, unhoused"
  },
  {
    "name": "BICHON RESCUE BRIDGADE",
    "ig_handle": "bichonsandbuddies",
    "breed_specific": ""
  },
  {
    "name": "BIG LOVES ANIMAL RESCUE",
    "ig_handle": "bigloveanimalrescue",
    "breed_specific": ""
  },
  {
    "name": "BLUE MAN DOG INC",
    "ig_handle": "bluemandog.inc",
    "breed_specific": ""
  },
  {
    "name": "BOOMERS BUDDIES RESCUE",
    "ig_handle": "BoomersBuddiesRescue",
    "breed_specific": ""
  },
  {
    "name": "BOSTON BUDDIES INC",
    "ig_handle": "bostonbuddies",
    "breed_specific": "BOSTON TERRIERS"
  },
  {
    "name": "BOXER RESCUE FUND",
    "ig_handle": "boxerrescuela",
    "breed_specific": ""
  },
  {
    "name": "BUBBLES DOG RESCUE",
    "ig_handle": "bubblesdogrescue",
    "breed_specific": ""
  },
  {
    "name": "BULLIES AND BUDDIES",
    "ig_handle": "bulliesandbuddies",
    "breed_specific": ""
  },
  {
    "name": "BUDDYS ANGELS INC",
    "ig_handle": "BuddysAngelsRescue",
    "breed_specific": ""
  },
  {
    "name": "CALIFORNIA DOODLE RESCUIE",
    "ig_handle": "californiadoodlerescues",
    "breed_specific": ""
  },
  {
    "name": "CALIFORNIA GSP INC",
    "ig_handle": "cagsprescue",
    "breed_specific": "GERMAN SHORT HAIR POINTERS"
  },
  {
    "name": "CALIFORNIA PAWS RESCUE",
    "ig_handle": "calpawsrescue",
    "breed_specific": "BULL TERRIER"
  },
  {
    "name": "CAMP COCKER RESCUE",
    "ig_handle": "campcockerrescue",
    "breed_specific": "COCKER SPANIEL"
  },
  {
    "name": "CHEWS LIFE DOG RESCUE",
    "ig_handle": "chewsliferescue",
    "breed_specific": ""
  },
  {
    "name": "COASTAL GERMAN SHEPHERD RESCUE",
    "ig_handle": "coastalgsr",
    "breed_specific": "GERMAN shepherd"
  },
  {
    "name": "COMMUITY ANIMAL MEDICINE PROJECT",
    "ig_handle": "campclinics",
    "breed_specific": ""
  },
  {
    "name": "DACHSCHUND RESCUE AND PLACEMEMT IC",
    "ig_handle": "dachshundrescuela",
    "breed_specific": ""
  },
  {
    "name": "DAISY SENRIOR DOG FOUNDATIONS",
    "ig_handle": "daisyluranch",
    "breed_specific": "SENIOR PUPS"
  },
  {
    "name": "DALMATION RESCUE OF SOUTHERN CA INC",
    "ig_handle": "spottyfriends",
    "breed_specific": ""
  },
  {
    "name": "DEATH ROW DOGS RESCUE",
    "ig_handle": "deathrowdogsrescue",
    "breed_specific": ""
  },
  {
    "name": "DEITY ANIMAL RESCUE",
    "ig_handle": "deityanimalrescue",
    "breed_specific": ""
  },
  {
    "name": "DOBIES AND LITTLE PAWS",
    "ig_handle": "dobiesandlittlepawsrescue",
    "breed_specific": "DOBERMAN"
  },
  {
    "name": "DOGS WITHOUT BORDERS",
    "ig_handle": "dogswithoutborders",
    "breed_specific": ""
  },
  {
    "name": "DOWNSTOWN DOG RESCUE",
    "ig_handle": "downtowndogrescue",
    "breed_specific": ""
  },
  {
    "name": "DREAM ANIMAL RESCUE",
    "ig_handle": "dreamanimalrescue",
    "breed_specific": ""
  },
  {
    "name": "DREAM TEAM ANGELS RSCUE",
    "ig_handle": "dreamteamangelsrescue",
    "breed_specific": ""
  },
  {
    "name": "EASTWOOD RANCH FOUNDATION",
    "ig_handle": "eastwoodranch",
    "breed_specific": ""
  },
  {
    "name": "ENGLISH SPRINGER RESCUE AMERICA",
    "ig_handle": "springerrescueamerica",
    "breed_specific": ""
  },
  {
    "name": "ESKIE RESCUERES UNITED AMERICAN ESKIMO",
    "ig_handle": "eskie_rescuers",
    "breed_specific": ""
  },
  {
    "name": "FETCHIN RETRIEVERS RESCUE",
    "ig_handle": "fetchinretrieversrescue",
    "breed_specific": ""
  },
  {
    "name": "FORGOTTEN PAWS ANIMAL RESCUE",
    "ig_handle": "4gottenpaws",
    "breed_specific": ""
  },
  {
    "name": "FORTE ANIMAL RESCUE",
    "ig_handle": "farescue",
    "breed_specific": ""
  },
  {
    "name": "FOXY AND THE HOUNDS",
    "ig_handle": "foxyandthehounds",
    "breed_specific": ""
  },
  {
    "name": "FRANKIE LOLA AND FRIENDS",
    "ig_handle": "lisachiarelli",
    "breed_specific": "Pit Bulls, black dogs, mama dogs, underdogs, all dogs"
  },
  {
    "name": "FRIENDS OF THE ANIMAL COMMUITY",
    "ig_handle": "friendsoftheanimalcommunity",
    "breed_specific": ""
  },
  {
    "name": "FROSTED FACES FOUDNATION INC",
    "ig_handle": "frostedfaces",
    "breed_specific": ""
  },
  {
    "name": "FURRY TAILS RESCUE",
    "ig_handle": "furry_tales_rescue",
    "breed_specific": ""
  },
  {
    "name": "GHETTO RESCUE FOUNDATION",
    "ig_handle": "GHETTORESCUE",
    "breed_specific": ""
  },
  {
    "name": "GIRLS OF DOG RSCUE",
    "ig_handle": "girlsofdogrescue",
    "breed_specific": ""
  },
  {
    "name": "GOLDEN RETREIVER CLUB OF GREATER LA RESCUE",
    "ig_handle": "grcglarescue",
    "breed_specific": ""
  },
  {
    "name": "GOLDEN YEARS DOG SANCTUARY",
    "ig_handle": "goldenyearsdogsanctuary",
    "breed_specific": "SENIORS"
  },
  {
    "name": "GONE TO THE DOGS RESCUE INC",
    "ig_handle": "gonetothedogsrescue",
    "breed_specific": ""
  },
  {
    "name": "GRAND PAWS SENIORS SANCTURAY",
    "ig_handle": "grandpawsseniorsanctuary",
    "breed_specific": "SENIORS"
  },
  {
    "name": "GREAT PYRANEES ASSOCATION OF SO CA RESCUE INC",
    "ig_handle": "greatpyrrescue",
    "breed_specific": ""
  },
  {
    "name": "GREEN DOG FOUNDATION",
    "ig_handle": "greendogfoundation",
    "breed_specific": ""
  },
  {
    "name": "HANKS LEGACY FOUNDATON",
    "ig_handle": "hankslegacyfoundation's",
    "breed_specific": ""
  },
  {
    "name": "HEART AND HOME ANIMAL RESCUE FOUNDATION",
    "ig_handle": "heartandhomerescueorg",
    "breed_specific": ""
  },
  {
    "name": "HENRYS HOPE FOUNDATION",
    "ig_handle": "henryshopefoundation",
    "breed_specific": ""
  },
  {
    "name": "HIT LIVING FOUNDATION",
    "ig_handle": "hitlivingfoundation",
    "breed_specific": ""
  },
  {
    "name": "HOLLYWOOD HUSKIES",
    "ig_handle": "hollywood_huskies",
    "breed_specific": "Huskies"
  },
  {
    "name": "HOOVES AND PAWS ANIMAL RESCUE",
    "ig_handle": "hoovesandpawsrescue",
    "breed_specific": ""
  },
  {
    "name": "HUSKY HAVEN OF LA INC",
    "ig_handle": "huskyhavenofla",
    "breed_specific": ""
  },
  {
    "name": "I STAND WITH MY PACK",
    "ig_handle": "istandwithmypack",
    "breed_specific": ""
  },
  {
    "name": "ICARE DOG RSCUE",
    "ig_handle": "icaredogrescue",
    "breed_specific": ""
  },
  {
    "name": "INDEPENDENT LABRADOR RETRIEVER RESCUE OF SO CA",
    "ig_handle": "indilabrescue",
    "breed_specific": ""
  },
  {
    "name": "INFINITE LOVE ANIMAL RESCUE",
    "ig_handle": "infiniteloverescue",
    "breed_specific": ""
  },
  {
    "name": "INTERNET MINI PINSCHER SERVICE",
    "ig_handle": "socal_imps_minpin_rescue",
    "breed_specific": ""
  },
  {
    "name": "JACK RUSSELL RESCUE CA INC",
    "ig_handle": "Jackrussellrescueca",
    "breed_specific": ""
  },
  {
    "name": "JJ WOOFIN PAWS RESCUE AGENCY",
    "ig_handle": "jjwoofinpawsrescue",
    "breed_specific": ""
  },
  {
    "name": "K9 KISMET DOG RESCUE",
    "ig_handle": "k9kismet",
    "breed_specific": "All breeds"
  },
  {
    "name": "K911 RSCUE INC",
    "ig_handle": "k911resq",
    "breed_specific": "Seniors, disabled"
  },
  {
    "name": "KARMA RESCUE INC",
    "ig_handle": "karmarescue",
    "breed_specific": ""
  },
  {
    "name": "KEN MAR RESCUE",
    "ig_handle": "kenmar_rescue",
    "breed_specific": "small dogs"
  },
  {
    "name": "LA ANIMAL RESCUE",
    "ig_handle": "laanimalrescue",
    "breed_specific": ""
  },
  {
    "name": "LANGE FOUNDATION",
    "ig_handle": "lange_foundation",
    "breed_specific": ""
  },
  {
    "name": "LEAGUE OF EXTRAORDINARY MUTTS",
    "ig_handle": "loemrescue",
    "breed_specific": ""
  },
  {
    "name": "LABROADORS AND FRIENDS DOG RESCUE GROUP INC",
    "ig_handle": "labsandfriends",
    "breed_specific": ""
  },
  {
    "name": "LEASHES OF LOVE RESCUE INC",
    "ig_handle": "lolrescue",
    "breed_specific": ""
  },
  {
    "name": "LEAVE NO PAWS BEHIND INC",
    "ig_handle": "leavenopawsbehind",
    "breed_specific": ""
  },
  {
    "name": "LEND A BONE INC",
    "ig_handle": "lendabone",
    "breed_specific": ""
  },
  {
    "name": "LIFE ANIMAL RESCUE",
    "ig_handle": "lifeanimalrescue",
    "breed_specific": ""
  },
  {
    "name": "LIILYS LEGACY SENIOR DOG SANCUTARY",
    "ig_handle": "lilyslegacyseniordogs",
    "breed_specific": ""
  },
  {
    "name": "LINDA BLAIR WORLDHEART FOUNDATION",
    "ig_handle": "lindablairwf",
    "breed_specific": ""
  },
  {
    "name": "LIVE LOVE ANIMAL SERVICES INC",
    "ig_handle": "liveloveanimalrescue",
    "breed_specific": ""
  },
  {
    "name": "LOVEBUGS RESCUES",
    "ig_handle": "lovebugsrescue",
    "breed_specific": ""
  },
  {
    "name": "LOVES LEGACY RESCUE",
    "ig_handle": "loveslegacyrescue",
    "breed_specific": ""
  },
  {
    "name": "MAD LOVE ANIMAL RESCUE",
    "ig_handle": "madloveanimalrescue",
    "breed_specific": ""
  },
  {
    "name": "MAE DAY INC",
    "ig_handle": "maedayrescue",
    "breed_specific": ""
  },
  {
    "name": "MAISON SURE FOUNDATION",
    "ig_handle": "maisonsurerescue",
    "breed_specific": ""
  },
  {
    "name": "MALETESE RESCUE CALIFORNAI",
    "ig_handle": "malteserescuecalifornia",
    "breed_specific": "Maltese & Maltese mixes"
  },
  {
    "name": "MARLEYS MUTTS DOG RESCUE",
    "ig_handle": "marleysmutts",
    "breed_specific": ""
  },
  {
    "name": "MARLEYS PIT STOP RESCUE",
    "ig_handle": "marleyspitstoprescue",
    "breed_specific": ""
  },
  {
    "name": "MAEDE CANINE RESCUE FOUNDATION",
    "ig_handle": "maedayrescue",
    "breed_specific": "All breeds/ages"
  },
  {
    "name": "MELITAS DREAM ANIMAL RESCUE",
    "ig_handle": "melitasdreamanimalrescue",
    "breed_specific": ""
  },
  {
    "name": "MILOS SANCTURARY INC",
    "ig_handle": "milos_sanctuary",
    "breed_specific": "Cats - Special-needs (disabled, seniors, hospice)"
  },
  {
    "name": "MINI SCHNAUZERS AND FRIENDS RESCUE",
    "ig_handle": "_msfr_",
    "breed_specific": "Mini Schnauzers & other small/companion breeds"
  },
  {
    "name": "MO4PAWS",
    "ig_handle": "mo4paws",
    "breed_specific": ""
  },
  {
    "name": "MUCH LOVE ANIMAL RESCUE",
    "ig_handle": "muchloveanimalrescue",
    "breed_specific": ""
  },
  {
    "name": "MUTTVILE",
    "ig_handle": "muttvillesf",
    "breed_specific": ""
  },
  {
    "name": "NEW BEGINNINGS FOR ANIMLAS",
    "ig_handle": "newbeginningsforanimals",
    "breed_specific": ""
  },
  {
    "name": "NO STRAY LEFT BEHIND",
    "ig_handle": "nslbrescue",
    "breed_specific": "Small-breed rescue"
  },
  {
    "name": "NOAHS BARK INC",
    "ig_handle": "noahs_bark_dog_rescue",
    "breed_specific": ""
  },
  {
    "name": "NORCAL BOXER RESCUE",
    "ig_handle": "norcal_boxer_rescue",
    "breed_specific": "Boxers; medical/urgent cases"
  },
  {
    "name": "NORTHERN CALIFRONIA WIEMARANER",
    "ig_handle": "norcalweimaranerrescue",
    "breed_specific": "Weimaraners"
  },
  {
    "name": "OC POM RESCUE",
    "ig_handle": "ocpomrescue",
    "breed_specific": "Pomeranians; foster-based, rehab focus"
  },
  {
    "name": "ONE DANE AT A TIME INC",
    "ig_handle": "onedaneatatime",
    "breed_specific": "Great Danes"
  },
  {
    "name": "ONE LOVE ANIMAL RESCUE AND SANCTUARY",
    "ig_handle": "oneloveanimalrescue",
    "breed_specific": ""
  },
  {
    "name": "ONE PLANET RESCUE",
    "ig_handle": "oneplanetrescue",
    "breed_specific": ""
  },
  {
    "name": "OPEN ARMS RESCUE",
    "ig_handle": "openarmsrescue",
    "breed_specific": "Small-dog rescue (SoCal/Baja pipeline)"
  },
  {
    "name": "ORANGE TWINS RESCUE",
    "ig_handle": "orangetwinsrescue",
    "breed_specific": ""
  },
  {
    "name": "OUTTA THE CAGE",
    "ig_handle": "outtathecage",
    "breed_specific": ""
  },
  {
    "name": "PACIFIC PUPS RESCUE",
    "ig_handle": "pacificpupsrescue",
    "breed_specific": "All breeds"
  },
  {
    "name": "PACK LYFE RESCUE",
    "ig_handle": "packlyferescue",
    "breed_specific": "All breeds"
  },
  {
    "name": "PASSION FOR PITTIES",
    "ig_handle": "passionforpitties",
    "breed_specific": "Pitbulls / Bully Breeds"
  },
  {
    "name": "PAW ESTATE RESCUE AND SHELTER INC",
    "ig_handle": "pawestaterescue",
    "breed_specific": "All breeds"
  },
  {
    "name": "PAW WORKS INC",
    "ig_handle": "pawworks",
    "breed_specific": ""
  },
  {
    "name": "PAWS FOR LIFE K9 RESCUE",
    "ig_handle": "pawsforlifek9",
    "breed_specific": "Small and mixed breeds"
  },
  {
    "name": "PAWS OF LA RESCUE",
    "ig_handle": "paws_la",
    "breed_specific": ""
  },
  {
    "name": "PAWSITIVE BEGINNINGS",
    "ig_handle": "pawsitivebeginningsla",
    "breed_specific": ""
  },
  {
    "name": "PEDRO PET PALS INC",
    "ig_handle": "PedroPetPals",
    "breed_specific": "All breeds"
  },
  {
    "name": "PET ADOPTION FUND",
    "ig_handle": "petadoptionfundrescue",
    "breed_specific": ""
  },
  {
    "name": "PET PLACE INTERNATIONAL INC",
    "ig_handle": "petplaceintl",
    "breed_specific": ""
  },
  {
    "name": "PET RESCUE SOLUTIONS",
    "ig_handle": "petrescuesolutions",
    "breed_specific": "Smalls, Shepherds, Labs"
  },
  {
    "name": "PETER ZIPPI FUND FOR ANIMALS",
    "ig_handle": "peterzippifund",
    "breed_specific": "Cats"
  },
  {
    "name": "PHU QUOC RIDGEBACK RESCUE NETWORK",
    "ig_handle": "Pqrrescue",
    "breed_specific": ""
  },
  {
    "name": "PRECIOUS PALS PET RESCUE",
    "ig_handle": "preciouspalspetrescue_official",
    "breed_specific": ""
  },
  {
    "name": "PROMISE 4 PAWS",
    "ig_handle": "promise4pawsrescue",
    "breed_specific": "All breeds"
  },
  {
    "name": "PRYORS PLANET",
    "ig_handle": "pryorsplanetrescue",
    "breed_specific": "All breeds"
  },
  {
    "name": "PUG NATION RESCUE OF LOS ANGELES INC",
    "ig_handle": "pugnationla",
    "breed_specific": ""
  },
  {
    "name": "PUP CULTURE RESCUE",
    "ig_handle": "pupculturerescue",
    "breed_specific": "All breeds"
  },
  {
    "name": "PUPS WITHOUT BORDERS",
    "ig_handle": "pupswithoutborders",
    "breed_specific": ""
  },
  {
    "name": "QUEENS BEST STUMPY DOG RESCUE",
    "ig_handle": "qbstumpydogrescue",
    "breed_specific": "Corgis"
  },
  {
    "name": "R&R BOXER RESCUE",
    "ig_handle": "rrboxerrescue",
    "breed_specific": "Boxers & other breeds"
  },
  {
    "name": "REAL GOOD RESCUE INC",
    "ig_handle": "realgoodrescue",
    "breed_specific": ""
  },
  {
    "name": "ROA DOGS & RESCUE",
    "ig_handle": "roadogs",
    "breed_specific": "Medical bulldogs, special needs & seniors"
  },
  {
    "name": "ROVERS RETREAT",
    "ig_handle": "roversretreat",
    "breed_specific": "Golden Retrievers & other breeds"
  },
  {
    "name": "RUSSELL RESCUE INC",
    "ig_handle": "russellrescueinc",
    "breed_specific": "Jack Russell Terriers"
  },
  {
    "name": "SAFE RESCUE TEAM",
    "ig_handle": "saferescueteam",
    "breed_specific": ""
  },
  {
    "name": "SAFFYRE SANCTUARY INC",
    "ig_handle": "saffyresanctuary",
    "breed_specific": "HORSES"
  },
  {
    "name": "SAMOYED RESCUE OF SOUTHERN CALIF",
    "ig_handle": "socalsamoyedrescue",
    "breed_specific": "Samoyeds"
  },
  {
    "name": "SAN DIEGO SPANIEL RESCUE",
    "ig_handle": "sandiegospanielrescue",
    "breed_specific": "Cocker Spaniels"
  },
  {
    "name": "SAVE A BOW WOW RESCUE",
    "ig_handle": "saveabowwowrescue",
    "breed_specific": "Small dogs"
  },
  {
    "name": "SAVE THE DALMATIANS AND OTHERS",
    "ig_handle": "savethedalsrescue",
    "breed_specific": "Dalmatians & other breeds"
  },
  {
    "name": "SAVING GIZMOS FRIENDS",
    "ig_handle": "savinggizmosfriends",
    "breed_specific": ""
  },
  {
    "name": "SAVING K9 LIVES PLUS",
    "ig_handle": "savingk9livesplus",
    "breed_specific": "Dogs from shelters & owner surrenders"
  },
  {
    "name": "SAVING SHIBAS INC",
    "ig_handle": "savingshibas",
    "breed_specific": "Shiba Inus"
  },
  {
    "name": "SECOND CHANCE COCKER RESCUE INC",
    "ig_handle": "secondchancecockerrescue",
    "breed_specific": "Cocker Spaniels"
  },
  {
    "name": "SHAWDOW HUSKY RESCUE INC",
    "ig_handle": "shadowhuskyrescue",
    "breed_specific": "Huskies"
  },
  {
    "name": "SHADOWS FUND INCORPORATED",
    "ig_handle": "shadowsfund",
    "breed_specific": "Senior dogs, pit bulls, Chows"
  },
  {
    "name": "SHAMROCK RESCUE FOUNDATION",
    "ig_handle": "shamrockrescuefoundation",
    "breed_specific": ""
  },
  {
    "name": "SHELTER TRANSPORT ANIMAL RESCUE TEAM",
    "ig_handle": "startrescue",
    "breed_specific": ""
  },
  {
    "name": "SHEPHERDS PAWS ANIMAL RESCUE",
    "ig_handle": "shepherds_paws_animal_rescue",
    "breed_specific": "Shepherds  & all breeds"
  },
  {
    "name": "SHY CLUB RESCUE",
    "ig_handle": "shyclubrescue",
    "breed_specific": ""
  },
  {
    "name": "SINGER SANCTUARY",
    "ig_handle": "singersanctuary",
    "breed_specific": ""
  },
  {
    "name": "SMOOCH POOCH DOG RESCUE",
    "ig_handle": "smoochpoochrescue",
    "breed_specific": ""
  },
  {
    "name": "SOCAL WEIMARANER RESCUE",
    "ig_handle": "socalweimrescue",
    "breed_specific": ""
  },
  {
    "name": "SOULAS WAY ANIMAL RESCUE",
    "ig_handle": "soulasway",
    "breed_specific": ""
  },
  {
    "name": "SOUTHERN CA BULLDOG RESCUE",
    "ig_handle": "socalbulldogrescue",
    "breed_specific": "bulldogs"
  },
  {
    "name": "SOUTHERN CA GOLDEN RETRIEVER RESCUE",
    "ig_handle": "scgrr",
    "breed_specific": "golden retrievers"
  },
  {
    "name": "SOUTHERN CA LABRADOR RET RESCUE",
    "ig_handle": "sclrr_lab_rescue",
    "breed_specific": "Labs"
  },
  {
    "name": "SOUTHERN CA PIT BULL RESCUE",
    "ig_handle": "socalpitbullrescue",
    "breed_specific": "Pit bulls"
  },
  {
    "name": "SOUTHERN CA POMERANIAN RESCUE",
    "ig_handle": "socalpomrescue",
    "breed_specific": "pomeranians"
  },
  {
    "name": "SOUTHERN CA SHIBA INU RESCUE INC",
    "ig_handle": "savingshibasinc",
    "breed_specific": "shiba inu"
  },
  {
    "name": "SOUTHLAND COLLIE RESCUE INC",
    "ig_handle": "southlandcollierescue",
    "breed_specific": ""
  },
  {
    "name": "SPARK RESCUE SANTA BARBARA INC",
    "ig_handle": "sparkrescue",
    "breed_specific": ""
  },
  {
    "name": "STACY HOPE RESCUE",
    "ig_handle": "staceyhoperescue",
    "breed_specific": ""
  },
  {
    "name": "SUNNY SAINTS SO CALIFORNIA SAINT BERNARD RESCUE",
    "ig_handle": "sunny_saints",
    "breed_specific": "St. Bernard"
  },
  {
    "name": "TAILS TO THE WIND ALL ANIMAL RESCUE",
    "ig_handle": "tailstothewind",
    "breed_specific": ""
  },
  {
    "name": "TAKE ME HOME",
    "ig_handle": "takemehomerescue",
    "breed_specific": ""
  },
  {
    "name": "TALES OF THE PAW RESCUE",
    "ig_handle": "tales.of.the.paw",
    "breed_specific": ""
  },
  {
    "name": "THE AMANDA FOUNDATION",
    "ig_handle": "amandafoundation",
    "breed_specific": ""
  },
  {
    "name": "THE ANIMAL RESCUE CENTER OF CALIFORNIA",
    "ig_handle": "thearcofca",
    "breed_specific": ""
  },
  {
    "name": "THE DADDIO COLLECTIVE",
    "ig_handle": "addiedaddio -- founder's personal insta",
    "breed_specific": ""
  },
  {
    "name": "THE DAWG SQUAD",
    "ig_handle": "dawgsquadmom",
    "breed_specific": ""
  },
  {
    "name": "THE DEXTER FOUNDATION DOG RESCUE",
    "ig_handle": "dexterfoundation",
    "breed_specific": ""
  },
  {
    "name": "THE JOY IN MY HEART FOUNDATION INC",
    "ig_handle": "thejoyinmyheart",
    "breed_specific": ""
  },
  {
    "name": "THE KRIS KELLY FOUNDATION",
    "ig_handle": "kriskellyfoundation",
    "breed_specific": ""
  },
  {
    "name": "THE LITTLE ANGELS PROJECT",
    "ig_handle": "thelittleangelsproject",
    "breed_specific": ""
  },
  {
    "name": "THE LITTLE RED DOG INC",
    "ig_handle": "thelittlereddog",
    "breed_specific": ""
  },
  {
    "name": "THE MUTT SCOUTS",
    "ig_handle": "muttscouts",
    "breed_specific": ""
  },
  {
    "name": "THE PAW MISSION",
    "ig_handle": "thePawmission",
    "breed_specific": ""
  },
  {
    "name": "THE PITTY COMMITTEE",
    "ig_handle": "thepittycommittee",
    "breed_specific": "Bully breeds -- pitbulls, etc"
  },
  {
    "name": "THE REAL BARK",
    "ig_handle": "therealbark",
    "breed_specific": ""
  },
  {
    "name": "THE RESCUE TRAIN",
    "ig_handle": "therescuetrain",
    "breed_specific": ""
  },
  {
    "name": "THE VANDERPUMP DOG FOUNDATION",
    "ig_handle": "vanderpumpdogs",
    "breed_specific": ""
  },
  {
    "name": "THE WRARE FOUNDATION",
    "ig_handle": "wrarefoundation",
    "breed_specific": ""
  },
  {
    "name": "THULANI SENIOR GERMAN SHEPHERDS RESCUE INC",
    "ig_handle": "thulani_gsdrescue",
    "breed_specific": "German Shepherd"
  },
  {
    "name": "TRINA & FRIENDS K-9 RESCUE INC",
    "ig_handle": "trinafriendsk9rescue",
    "breed_specific": "German Shepherd"
  },
  {
    "name": "TWO DOG FARMS INC",
    "ig_handle": "twodogfarms",
    "breed_specific": "Jindo"
  },
  {
    "name": "UNDER ONE SKY ANIMAL RESCUE",
    "ig_handle": "underoneskyrescue",
    "breed_specific": "CATS"
  },
  {
    "name": "UNDERDOG HEROES",
    "ig_handle": "underdogheroes_",
    "breed_specific": ""
  },
  {
    "name": "VIP RQ",
    "ig_handle": "vip_rsq",
    "breed_specific": ""
  },
  {
    "name": "VOICE FOR THE ANIMALS",
    "ig_handle": "vftafoundation",
    "breed_specific": ""
  },
  {
    "name": "WAGMOR PETS",
    "ig_handle": "wagmorpets",
    "breed_specific": ""
  },
  {
    "name": "WAGS AND WALKS",
    "ig_handle": "wagsandwalks",
    "breed_specific": ""
  },
  {
    "name": "WELCOME HOME DOG RESCUE",
    "ig_handle": "welcomehomedogrescue",
    "breed_specific": ""
  },
  {
    "name": "WEST COAST LABRADOR RETRIEVER RESCUE",
    "ig_handle": "wclrr",
    "breed_specific": "Labs"
  },
  {
    "name": "WESTSIDE GERMAN SHEPHERD RESCUE",
    "ig_handle": "westsidegsr",
    "breed_specific": "German Shepherd"
  },
  {
    "name": "WHAT ABOUT LOVE ANIMAL RESCUE INC",
    "ig_handle": "whataboutloveanimalrescue",
    "breed_specific": ""
  },
  {
    "name": "WHITTIER AREA DOG RESCUE",
    "ig_handle": "whittierareadogrescue",
    "breed_specific": ""
  },
  {
    "name": "WISHBONE DOG RESCUE",
    "ig_handle": "wishbone_rescue",
    "breed_specific": ""
  },
  {
    "name": "WOMEN UNITED FOR ANIMAL WELFARE",
    "ig_handle": "wufaw_official",
    "breed_specific": ""
  }
]
